torchextractor/__init__.py
torchextractor/extractor.py
torchextractor/naming.py
torchextractor/version.py
torchextractor-0.3.0.dist-info/LICENSE
torchextractor-0.3.0.dist-info/METADATA
torchextractor-0.3.0.dist-info/WHEEL
torchextractor-0.3.0.dist-info/top_level.txt
torchextractor-0.3.0.dist-info/RECORD
