Metadata-Version: 2.1
Name: torchextractor
Version: 0.3.0
Summary: Pytorch feature extraction made simple
Home-page: https://github.com/antoinebrl/torchextractor
Author: Antoine Broyelle
Author-email: antoine.broyelle@pm.me
License: UNKNOWN
Project-URL: Bug Tracker, https://github.com/antoinebrl/torchextractor/issues
Keywords: pytorch torch feature extraction
Platform: UNKNOWN
Classifier: Development Status :: 4 - Beta
Classifier: Natural Language :: English
Classifier: License :: OSI Approved :: Apache Software License
Classifier: Operating System :: OS Independent
Classifier: Intended Audience :: Education
Classifier: Intended Audience :: Developers
Classifier: Intended Audience :: Science/Research
Classifier: Topic :: Scientific/Engineering
Classifier: Topic :: Scientific/Engineering :: Artificial Intelligence
Classifier: Topic :: Software Development
Classifier: Topic :: Software Development :: Libraries
Classifier: Topic :: Software Development :: Libraries :: Python Modules
Classifier: Programming Language :: Python :: 3
Classifier: Programming Language :: Python :: 3 :: Only
Classifier: Programming Language :: Python :: 3.6
Classifier: Programming Language :: Python :: 3.7
Classifier: Programming Language :: Python :: 3.8
Classifier: Programming Language :: Python :: 3.9
Requires-Python: >=3.6
Requires-Dist: numpy
Requires-Dist: torch (>=1.4.0)
